mcskin/__init__.py
mcskin/__main__.py
mcskin/models/resnet10/anime_style_noise0_rgb.npz
mcskin/models/resnet10/anime_style_noise0_y.npz
mcskin/models/resnet10/anime_style_noise1_rgb.npz
mcskin/models/resnet10/anime_style_noise1_y.npz
mcskin/models/resnet10/anime_style_noise2_rgb.npz
mcskin/models/resnet10/anime_style_noise2_y.npz
mcskin/models/resnet10/anime_style_noise3_rgb.npz
mcskin/models/resnet10/anime_style_noise3_y.npz
mcskin/models/resnet10/anime_style_scale_rgb.npz
mcskin/models/resnet10/anime_style_scale_y.npz
mcskin/models/upconv7/anime_style_noise0_scale_rgb.npz
mcskin/models/upconv7/anime_style_noise1_scale_rgb.npz
mcskin/models/upconv7/anime_style_noise2_scale_rgb.npz
mcskin/models/upconv7/anime_style_noise3_scale_rgb.npz
mcskin/models/upconv7/anime_style_scale_rgb.npz
mcskin/models/upresnet10/anime_style_noise0_scale_rgb.npz
mcskin/models/upresnet10/anime_style_noise1_scale_rgb.npz
mcskin/models/upresnet10/anime_style_noise2_scale_rgb.npz
mcskin/models/upresnet10/anime_style_noise3_scale_rgb.npz
mcskin/models/upresnet10/anime_style_scale_rgb.npz
mcskin/models/vgg7/anime_style_noise0_rgb.npz
mcskin/models/vgg7/anime_style_noise0_y.npz
mcskin/models/vgg7/anime_style_noise1_rgb.npz
mcskin/models/vgg7/anime_style_noise1_y.npz
mcskin/models/vgg7/anime_style_noise2_rgb.npz
mcskin/models/vgg7/anime_style_noise2_y.npz
mcskin/models/vgg7/anime_style_noise3_rgb.npz
mcskin/models/vgg7/anime_style_noise3_y.npz
mcskin/models/vgg7/anime_style_scale_rgb.npz
mcskin/models/vgg7/anime_style_scale_y.npz
mcskin-2024.0.1.dist-info/entry_points.txt
mcskin-2024.0.1.dist-info/LICENSE.md
mcskin-2024.0.1.dist-info/METADATA
mcskin-2024.0.1.dist-info/WHEEL
mcskin-2024.0.1.dist-info/RECORD
