Metadata-Version: 2.1
Name: mcskin
Version: 2024.0.1
Summary: For some raw skin, generate 1.0, 1.8 and 1.8 bedrock skins.
Home-page: https://github.com/FHPythonUtils/MCSkin
License: MIT
Author: FredHappyface
Requires-Python: >=3.9,<3.12
Classifier: Development Status :: 5 - Production/Stable
Classifier: Environment :: Console
Classifier: Environment :: MacOS X
Classifier: Environment :: Win32 (MS Windows)
Classifier: Intended Audience :: Developers
Classifier: Intended Audience :: Education
Classifier: License :: OSI Approved :: MIT License
Classifier: Natural Language :: English
Classifier: Operating System :: OS Independent
Classifier: Programming Language :: Python :: 3
Classifier: Programming Language :: Python :: 3.9
Classifier: Programming Language :: Python :: 3.10
Classifier: Programming Language :: Python :: 3.11
Classifier: Programming Language :: Python :: Implementation :: CPython
Classifier: Topic :: Software Development :: Libraries :: Python Modules
Classifier: Topic :: Utilities
Requires-Dist: Pillow (>=10.2.0,<11)
Requires-Dist: layeredimage (>=2024.2.1,<2026)
Requires-Dist: waifu2x (>=2024,<2026)
Project-URL: Documentation, https://github.com/FHPythonUtils/MCSkin/blob/master/README.md
Project-URL: Repository, https://github.com/FHPythonUtils/MCSkin
